{
  "card": {
    "attack": 10,
    "hp": 1,
    "maxHp": 1,
    "originalAttack": 10,
    "originalHp": 1,
    "dodge": 0,
    "armor": 0,
    "paralyzed": 0,
    "silence": false,
    "kr": 0,
    "burn": 0,
    "cantAttack": false,
    "charge": false,
    "taunt": false,
    "invulnerable": false,
    "haste": false,
    "transparency": false,
    "candy": false,
    "id": 110,
    "fixedId": 110,
    "typeCard": 0,
    "name": "Mettaton NEO",
    "image": "Mettaton_NEO",
    "baseImage": "Mettaton_NEO",
    "cost": 10,
    "rarity": "LEGENDARY",
    "originalCost": 10,
    "shiny": false,
    "quantity": 1,
    "extension": "BASE",
    "tribes": [],
    "selectCards": [],
    "typeSkin": 0,
    "playedTurn": 0,
    "ownerId": 0,
    "description": "{{KW:DUST}}: Deal {{DMG}} equal to its {{ATK}} to all monsters and half to the opponent."
  },
  "diffs": {
    "added": {},
    "removed": {
      "creatorFixedId": 0
    },
    "changed": {}
  }
}