{
  "card": {
    "attack": 4,
    "hp": 4,
    "maxHp": 4,
    "originalAttack": 4,
    "originalHp": 4,
    "dead": false,
    "id": 161,
    "fixedId": 161,
    "typeCard": 0,
    "name": "Clam Girl",
    "image": "Clam_Girl",
    "baseImage": "Clam_Girl",
    "cost": 5,
    "rarity": "RARE",
    "originalCost": 5,
    "shiny": false,
    "quantity": 1,
    "extension": "BASE",
    "tribes": [],
    "selectCards": [],
    "typeSkin": 0,
    "playedTurn": 0,
    "ownerId": 0,
    "statuses": [],
    "description": ""
  },
  "diffs": {
    "added": {},
    "removed": {},
    "changed": {}
  }
}