{
  "card": {
    "attack": 5,
    "hp": 9,
    "maxHp": 9,
    "originalAttack": 5,
    "originalHp": 9,
    "dodge": 0,
    "thorns": 0,
    "armor": 0,
    "paralyzed": 0,
    "silence": false,
    "kr": 0,
    "burn": 0,
    "cantAttack": false,
    "charge": false,
    "taunt": false,
    "ranged": false,
    "invulnerable": false,
    "haste": false,
    "transparency": false,
    "anotherChance": false,
    "candy": false,
    "id": 17,
    "fixedId": 17,
    "typeCard": 0,
    "name": "Knight Knight",
    "image": "Knight_Knight",
    "baseImage": "Knight_Knight",
    "cost": 9,
    "rarity": "COMMON",
    "originalCost": 9,
    "shiny": false,
    "quantity": 1,
    "extension": "BASE",
    "tribes": [],
    "selectCards": [],
    "typeSkin": 0,
    "playedTurn": 0,
    "ownerId": 0,
    "creatorFixedId": 0,
    "imageExtension": "png",
    "description": "After this attacks, heal itself by the amount of {{DMG}} dealt."
  },
  "diffs": {
    "added": {
      "burn": 0,
      "baseImage": "Knight_Knight",
      "playedTurn": 0
    },
    "removed": {},
    "changed": {}
  }
}