{
  "card": {
    "attack": 4,
    "hp": 3,
    "maxHp": 3,
    "originalAttack": 4,
    "originalHp": 3,
    "dodge": 0,
    "armor": false,
    "paralyzed": 0,
    "silence": false,
    "kr": false,
    "burn": 0,
    "cantAttack": false,
    "charge": false,
    "taunt": false,
    "invulnerable": false,
    "haste": false,
    "transparency": false,
    "candy": false,
    "shockEnabled": false,
    "supportEnabled": false,
    "wanted": false,
    "darkspawn": false,
    "id": 177,
    "fixedId": 177,
    "typeCard": 0,
    "name": "Redacted",
    "image": "Redacted",
    "baseImage": "Redacted",
    "cost": 5,
    "rarity": "RARE",
    "originalCost": 5,
    "target": "ENEMY_MONSTER",
    "shiny": false,
    "quantity": 1,
    "extension": "BASE",
    "tribes": [
      "G_FOLLOWER"
    ],
    "selectCards": [],
    "typeSkin": 0,
    "playedTurn": 0,
    "ownerId": 0,
    "bullseyeEnabled": false,
    "loop": 0,
    "program": 0,
    "description": ""
  },
  "diffs": {
    "added": {
      "darkspawn": false
    },
    "removed": {},
    "changed": {}
  }
}