{
  "card": {
    "attack": 3,
    "hp": 6,
    "maxHp": 6,
    "originalAttack": 3,
    "originalHp": 6,
    "dodge": 0,
    "thorns": 0,
    "armor": 0,
    "paralyzed": 0,
    "silence": false,
    "kr": 0,
    "burn": 0,
    "cantAttack": false,
    "charge": false,
    "taunt": true,
    "ranged": false,
    "invulnerable": false,
    "haste": false,
    "transparency": false,
    "anotherChance": false,
    "candy": false,
    "id": 218,
    "fixedId": 218,
    "typeCard": 0,
    "name": "Receptionist 3",
    "image": "Receptionist_3",
    "baseImage": "Receptionist_3",
    "cost": 3,
    "rarity": "EPIC",
    "originalCost": 3,
    "shiny": false,
    "quantity": 1,
    "extension": "BASE",
    "tribes": [],
    "selectCards": [],
    "typeSkin": 0,
    "playedTurn": 0,
    "ownerId": 0,
    "creatorFixedId": 0,
    "imageExtension": "png",
    "description": "{{KW:TAUNT}}. {{KW:MAGIC}}: Summon a random enemy monster from his hand if his board isn't full."
  },
  "diffs": {
    "added": {
      "burn": 0,
      "baseImage": "Receptionist_3",
      "playedTurn": 0
    },
    "removed": {},
    "changed": {}
  }
}