{
  "card": {
    "attack": 2,
    "hp": 1,
    "maxHp": 1,
    "originalAttack": 2,
    "originalHp": 1,
    "dodge": 0,
    "thorns": 0,
    "armor": 0,
    "paralyzed": 0,
    "silence": false,
    "kr": 0,
    "burn": 0,
    "cantAttack": false,
    "charge": false,
    "taunt": false,
    "ranged": false,
    "invulnerable": false,
    "haste": false,
    "transparency": false,
    "anotherChance": false,
    "candy": false,
    "id": 307,
    "fixedId": 307,
    "typeCard": 0,
    "name": "Bloody Tree",
    "image": "Bloody_Tree",
    "baseImage": "Bloody_Tree",
    "cost": 2,
    "rarity": "COMMON",
    "originalCost": 2,
    "target": "ALLY_MONSTER",
    "shiny": false,
    "quantity": 1,
    "extension": "DELTARUNE",
    "tribes": [
      "PLANT"
    ],
    "selectCards": [],
    "typeSkin": 0,
    "playedTurn": 0,
    "ownerId": 0,
    "creatorFixedId": 0,
    "imageExtension": "png",
    "description": "{{KW:MAGIC}}: Trigger the {{KW:DUST}} effect of an ally monster that costs 3 or less."
  },
  "diffs": {
    "added": {
      "burn": 0,
      "baseImage": "Bloody_Tree",
      "playedTurn": 0
    },
    "removed": {},
    "changed": {}
  }
}