{
  "card": {
    "attack": 3,
    "hp": 2,
    "maxHp": 2,
    "originalAttack": 3,
    "originalHp": 2,
    "dodge": 0,
    "thorns": 0,
    "armor": 0,
    "paralyzed": 0,
    "silence": false,
    "kr": 0,
    "cantAttack": false,
    "charge": false,
    "taunt": false,
    "ranged": false,
    "invulnerable": false,
    "haste": false,
    "transparency": false,
    "anotherChance": false,
    "candy": false,
    "id": 4,
    "fixedId": 4,
    "typeCard": 0,
    "name": "Moldsmal",
    "image": "Moldsmal",
    "cost": 2,
    "rarity": "BASE",
    "originalCost": 2,
    "shiny": false,
    "quantity": 1,
    "extension": "BASE",
    "tribes": [
      "MOLD"
    ],
    "selectCards": [],
    "typeSkin": 0,
    "ownerId": 0,
    "creatorFixedId": 0,
    "imageExtension": "png",
    "description": ""
  },
  "diffs": {
    "added": {
      "tribes": [
        "MOLD"
      ],
      "typeSkin": 0,
      "creatorFixedId": 0
    },
    "removed": {
      "tribe": "MOLD"
    },
    "changed": {}
  }
}