{
  "card": {
    "attack": 1,
    "hp": 1,
    "maxHp": 1,
    "originalAttack": 1,
    "originalHp": 1,
    "dodge": 0,
    "armor": 0,
    "paralyzed": 0,
    "silence": false,
    "kr": 0,
    "burn": 0,
    "cantAttack": false,
    "charge": false,
    "taunt": false,
    "invulnerable": false,
    "haste": true,
    "transparency": false,
    "candy": false,
    "id": 433,
    "fixedId": 433,
    "typeCard": 0,
    "name": "Butterflies",
    "image": "Butterflies",
    "baseImage": "Butterflies",
    "cost": 1,
    "rarity": "COMMON",
    "originalCost": 1,
    "shiny": false,
    "quantity": 1,
    "extension": "BASE",
    "tribes": [],
    "selectCards": [],
    "typeSkin": 0,
    "playedTurn": 0,
    "ownerId": 0,
    "description": "{{KW:HASTE}}. {{KW:DUST}}: Add a random <= 3 {{GOLD}} spell to your hand."
  },
  "diffs": {
    "added": {},
    "removed": {},
    "changed": {}
  }
}