{
  "card": {
    "id": 516,
    "fixedId": 516,
    "typeCard": 1,
    "name": "Breaking Love",
    "image": "Breaking_Love",
    "baseImage": "Breaking_Love",
    "cost": 1,
    "rarity": "TOKEN",
    "originalCost": 1,
    "target": "ENEMY_MONSTER",
    "shiny": false,
    "quantity": 1,
    "extension": "DELTARUNE",
    "tribes": [],
    "selectCards": [],
    "typeSkin": 0,
    "playedTurn": 0,
    "ownerId": 0,
    "description": "Give an enemy monster -1/-1. Draw a card."
  },
  "diffs": {
    "added": {},
    "removed": {},
    "changed": {}
  }
}