{
  "card": {
    "attack": 6,
    "hp": 6,
    "maxHp": 6,
    "originalAttack": 6,
    "originalHp": 6,
    "dead": false,
    "id": 630,
    "fixedId": 630,
    "typeCard": 0,
    "name": "Shovels x999",
    "image": "Shovels_x999",
    "baseImage": "Shovels_x999",
    "cost": 6,
    "rarity": "EPIC",
    "originalCost": 6,
    "shiny": false,
    "quantity": 1,
    "extension": "DELTARUNE",
    "tribes": [],
    "selectCards": [],
    "typeSkin": 0,
    "playedTurn": 0,
    "ownerId": 0,
    "statuses": [],
    "description": ""
  },
  "diffs": {
    "added": {},
    "removed": {},
    "changed": {}
  }
}