{
  "card": {
    "soul": {
      "id": 6,
      "name": "PATIENCE"
    },
    "id": 72,
    "fixedId": 72,
    "typeCard": 1,
    "name": "Slowing",
    "image": "Slowing",
    "baseImage": "Slowing",
    "cost": 4,
    "rarity": "COMMON",
    "originalCost": 4,
    "target": "ENEMY_MONSTER",
    "shiny": false,
    "quantity": 1,
    "extension": "BASE",
    "tribes": [],
    "selectCards": [],
    "typeSkin": 0,
    "playedTurn": 0,
    "ownerId": 0,
    "creatorFixedId": 0,
    "imageExtension": "png",
    "description": "Send a paralyzed enemy monster to your opponent's deck."
  },
  "diffs": {
    "added": {
      "baseImage": "Slowing",
      "playedTurn": 0
    },
    "removed": {},
    "changed": {}
  }
}