{
  "card": {
    "soul": {
      "id": 1,
      "name": "BRAVERY"
    },
    "id": 79,
    "fixedId": 79,
    "typeCard": 1,
    "name": "Penetration",
    "image": "Penetration",
    "baseImage": "Penetration",
    "cost": 1,
    "rarity": "RARE",
    "originalCost": 1,
    "target": "MONSTER",
    "shiny": false,
    "quantity": 1,
    "extension": "BASE",
    "tribes": [],
    "selectCards": [],
    "typeSkin": 0,
    "playedTurn": 0,
    "ownerId": 0,
    "bullseyeEnabled": false,
    "loop": 0,
    "program": 0,
    "description": ""
  },
  "diffs": {
    "added": {},
    "removed": {},
    "changed": {
      "description": {
        "now": "",
        "prev": "{{KW:SILENCE}} a monster."
      }
    }
  }
}